B2cNews/__init__.py
B2cNews/main.py
B2cNews-2.1.dist-info/METADATA
B2cNews-2.1.dist-info/WHEEL
B2cNews-2.1.dist-info/entry_points.txt
B2cNews-2.1.dist-info/top_level.txt
B2cNews-2.1.dist-info/RECORD
