Metadata-Version: 2.1
Name: B2cNews
Version: 2.1
Requires-Dist: requests
Requires-Dist: beautifulsoup4
Requires-Dist: pandas
